{"author":"Hippolytus","book":"Fragments from Other Writings of Hippolytus.","chapter":2,"classification":{"bucket":"Patristic / broadly orthodox","canonicalStatus":"patristic","contentKind":"primary","cautionReason":"No major mainstream heresy warning is attached by the preview classifier.","doctrinalStatus":"orthodox","labels":["patristic"],"severity":0},"id":"anf05:iii.iv.ii.viii.ii","lineage":["Hippolytus.","The Extant Works and Fragments of Hippolytus.","Dogmatical and Historical.","Fragments from Other Writings of Hippolytus.","From the same."],"metadata":{"author":"Hippolytus","authorshipDateRange":"third century","ccel":{"id":"anf05","sourceUrl":"https://www.ccel.org/ccel/schaff/anf05.xml","title":"ANF05. Fathers of the Third Century: Hippolytus, Cyprian, Caius, Novatian, Appendix"},"source":{"id":"anf05","provider":"CCEL","sourceUrl":"https://www.ccel.org/ccel/schaff/anf05.xml","title":"ANF05. Fathers of the Third Century: Hippolytus, Cyprian, Caius, Novatian, Appendix"}},"originalBook":null,"sourceVolumeId":"anf05","title":"From the same.","source":{"id":"anf05","sourceUrl":"https://www.ccel.org/ccel/schaff/anf05.xml","title":"ANF05. Fathers of the Third Century: Hippolytus, Cyprian, Caius, Novatian, Appendix"},"verses":[{"book":"Fragments from Other Writings of Hippolytus.","chapter":2,"text":"And again the same (authority), in the first book of his treatise on the Holy Supper, speaks thus:—","verse":1},{"book":"Fragments from Other Writings of Hippolytus.","chapter":2,"text":"Now that neither in the first nor in the last there was anything false is evident; for he who said of old, “I will not any more eat the passover,” probably partook of supper before the passover.","verse":2},{"book":"Fragments from Other Writings of Hippolytus.","chapter":2,"text":"But the passover He did not eat, but He suffered; for it was not the time for Him to eat.","verse":3}]}