{"author":"Hippolytus","book":"Against Beron and Helix.","chapter":7,"classification":{"bucket":"Patristic / broadly orthodox","canonicalStatus":"patristic","contentKind":"primary","cautionReason":"No major mainstream heresy warning is attached by the preview classifier.","doctrinalStatus":"orthodox","labels":["patristic"],"severity":0},"id":"anf05:iii.iv.ii.v.vii","lineage":["Hippolytus.","The Extant Works and Fragments of Hippolytus.","Dogmatical and Historical.","Against Beron and Helix.","Fragment VII."],"metadata":{"author":"Hippolytus","authorshipDateRange":"third century","ccel":{"id":"anf05","sourceUrl":"https://www.ccel.org/ccel/schaff/anf05.xml","title":"ANF05. Fathers of the Third Century: Hippolytus, Cyprian, Caius, Novatian, Appendix"},"source":{"id":"anf05","provider":"CCEL","sourceUrl":"https://www.ccel.org/ccel/schaff/anf05.xml","title":"ANF05. Fathers of the Third Century: Hippolytus, Cyprian, Caius, Novatian, Appendix"}},"originalBook":null,"sourceVolumeId":"anf05","title":"Fragment VII.","source":{"id":"anf05","sourceUrl":"https://www.ccel.org/ccel/schaff/anf05.xml","title":"ANF05. Fathers of the Third Century: Hippolytus, Cyprian, Caius, Novatian, Appendix"},"verses":[{"book":"Against Beron and Helix.","chapter":7,"text":"But if it (the flesh) did not become of like nature with that (the deity), neither shall it ever become of like natural energy with that; that He may not be shown to have His energy unequal with His nature, and heterogeneous, and, through all that pertains to Himself, to have entered on an existence outside of His natural equality and identity, which is an impious supposition.","verse":1}]}