{"author":"POLYCARP","book":"Epistle to the Philippians","chapter":14,"classification":{"bucket":"Patristic / broadly orthodox","canonicalStatus":"patristic","contentKind":"primary","cautionReason":"No major mainstream heresy warning is attached by the preview classifier.","doctrinalStatus":"orthodox","labels":["patristic"],"severity":0},"id":"anf01:iv.ii.xiv","lineage":["POLYCARP","Epistle to the Philippians","Chapter XIV.—Conclusion."],"metadata":{"author":"POLYCARP","authorshipDateRange":null,"ccel":{"id":"anf01","sourceUrl":"https://www.ccel.org/ccel/schaff/anf01.xml","title":"ANF01. The Apostolic Fathers with Justin Martyr and Irenaeus"},"source":{"id":"anf01","provider":"CCEL","sourceUrl":"https://www.ccel.org/ccel/schaff/anf01.xml","title":"ANF01. The Apostolic Fathers with Justin Martyr and Irenaeus"}},"originalBook":null,"sourceVolumeId":"anf01","title":"Chapter XIV.—Conclusion.","source":{"id":"anf01","sourceUrl":"https://www.ccel.org/ccel/schaff/anf01.xml","title":"ANF01. The Apostolic Fathers with Justin Martyr and Irenaeus"},"verses":[{"book":"Epistle to the Philippians","chapter":14,"text":"These things I have written to you by Crescens, whom up to the present time I have recommended unto you, and do now recommend.","verse":1},{"book":"Epistle to the Philippians","chapter":14,"text":"For he has acted blamelessly among us, and I believe also among you.","verse":2},{"book":"Epistle to the Philippians","chapter":14,"text":"Moreover, ye will hold his sister in esteem when she comes to you.","verse":3},{"book":"Epistle to the Philippians","chapter":14,"text":"Be ye safe in the Lord Jesus Christ.","verse":4},{"book":"Epistle to the Philippians","chapter":14,"text":"Grace be with you all.","verse":5}]}