{"author":"Hippolytus","book":"On the Psalms.","chapter":3,"classification":{"bucket":"Patristic / broadly orthodox","canonicalStatus":"patristic","contentKind":"primary","cautionReason":"No major mainstream heresy warning is attached by the preview classifier.","doctrinalStatus":"orthodox","labels":["patristic"],"severity":0},"id":"anf05:iii.iv.i.xiv.iii","lineage":["Hippolytus.","The Extant Works and Fragments of Hippolytus.","Exegetical.","On the Psalms.","On Psalm lv. 15."],"metadata":{"author":"Hippolytus","authorshipDateRange":"third century","ccel":{"id":"anf05","sourceUrl":"https://www.ccel.org/ccel/schaff/anf05.xml","title":"ANF05. Fathers of the Third Century: Hippolytus, Cyprian, Caius, Novatian, Appendix"},"source":{"id":"anf05","provider":"CCEL","sourceUrl":"https://www.ccel.org/ccel/schaff/anf05.xml","title":"ANF05. Fathers of the Third Century: Hippolytus, Cyprian, Caius, Novatian, Appendix"}},"originalBook":null,"sourceVolumeId":"anf05","title":"On Psalm lv. 15.","source":{"id":"anf05","sourceUrl":"https://www.ccel.org/ccel/schaff/anf05.xml","title":"ANF05. Fathers of the Third Century: Hippolytus, Cyprian, Caius, Novatian, Appendix"},"verses":[{"book":"On the Psalms.","chapter":3,"text":"One of old used to say that those only descend alive into Hades who are instructed in the knowledge of things divine; for he who has not tasted of the words of life is dead.","verse":1}]}