{"author":"The Life of Constantine with Orations of Constantine and Eusebius","book":"The Life of Constantine.","chapter":152,"classification":{"bucket":"Patristic / broadly orthodox","canonicalStatus":"patristic","contentKind":"primary","cautionReason":"No major mainstream heresy warning is attached by the preview classifier.","doctrinalStatus":"orthodox","labels":["patristic"],"severity":0},"id":"npnf201:iv.vi.iii.xx","lineage":["The Life of Constantine with Orations of Constantine and Eusebius.","The Life of Constantine.","Book III","Exhortation to obey the Decrees of the Council."],"metadata":{"author":"The Life of Constantine with Orations of Constantine and Eusebius","authorshipDateRange":null,"ccel":{"id":"npnf201","sourceUrl":"https://www.ccel.org/ccel/schaff/npnf201.xml","title":"NPNF2-01. Eusebius Pamphilius: Church History, Life of Constantine, Oration in Praise of Constantine"},"source":{"id":"npnf201","provider":"CCEL","sourceUrl":"https://www.ccel.org/ccel/schaff/npnf201.xml","title":"NPNF2-01. Eusebius Pamphilius: Church History, Life of Constantine, Oration in Praise of Constantine"}},"originalBook":"Book III","sourceVolumeId":"npnf201","title":"Exhortation to obey the Decrees of the Council.","source":{"id":"npnf201","sourceUrl":"https://www.ccel.org/ccel/schaff/npnf201.xml","title":"NPNF2-01. Eusebius Pamphilius: Church History, Life of Constantine, Oration in Praise of Constantine"},"verses":[{"book":"The Life of Constantine.","chapter":152,"text":"“Receive, then, with all willingness this truly Divine injunction, and regard it as in truth the gift of God.","verse":1},{"book":"The Life of Constantine.","chapter":152,"text":"For whatever is determined in the holy assemblies of the bishops is to be regarded as indicative of the Divine will.","verse":2},{"book":"The Life of Constantine.","chapter":152,"text":"As soon, therefore, as you have communicated these proceedings to all our beloved brethren, you are bound from that time forward to adopt for yourselves, and to enjoin on others the arrangement above mentioned, and the due observance of this most sacred day; that whenever I come into the presence of your love, which I have long desired, I may have it in my power to celebrate the holy feast with you on the same day, and may rejoice with you on all accounts, when I behold the cruel power of Satan removed by Divine aid through the agency of our endeavors, while your faith, and peace, and concord everywhere flourish.","verse":3},{"book":"The Life of Constantine.","chapter":152,"text":"God preserve you, beloved brethren!”","verse":4},{"book":"The Life of Constantine.","chapter":152,"text":"The emperor transmitted a faithful copy of this letter to every province, wherein they who read it might discern as in a mirror the pure sincerity of his thoughts, and of his piety toward God.","verse":5}]}