{"author":"Eusebius of Caesarea","book":"The Church History of Eusebius.","chapter":191,"classification":{"bucket":"Patristic / broadly orthodox","canonicalStatus":"patristic","contentKind":"primary","cautionReason":"No major mainstream heresy warning is attached by the preview classifier.","doctrinalStatus":"orthodox","labels":["patristic"],"severity":0},"id":"npnf201:iii.xii.iv","lineage":["The Church History of Eusebius.","Book VII","Cyprian, and the Bishops with him, first taught that it was necessary to purify by Baptism those converted from Heresy."],"metadata":{"author":"Eusebius of Caesarea","authorshipDateRange":null,"ccel":{"id":"npnf201","sourceUrl":"https://www.ccel.org/ccel/schaff/npnf201.xml","title":"NPNF2-01. Eusebius Pamphilius: Church History, Life of Constantine, Oration in Praise of Constantine"},"source":{"id":"npnf201","provider":"CCEL","sourceUrl":"https://www.ccel.org/ccel/schaff/npnf201.xml","title":"NPNF2-01. Eusebius Pamphilius: Church History, Life of Constantine, Oration in Praise of Constantine"}},"originalBook":"Book VII","sourceVolumeId":"npnf201","title":"Cyprian, and the Bishops with him, first taught that it was necessary to purify by Baptism those converted from Heresy.","source":{"id":"npnf201","sourceUrl":"https://www.ccel.org/ccel/schaff/npnf201.xml","title":"NPNF2-01. Eusebius Pamphilius: Church History, Life of Constantine, Oration in Praise of Constantine"},"verses":[{"book":"The Church History of Eusebius.","chapter":191,"text":"First of all, Cyprian, pastor of the parish of Carthage, maintained that they should not be received except they had been purified from their error by baptism.","verse":1},{"book":"The Church History of Eusebius.","chapter":191,"text":"But Stephen considering it unnecessary to add any innovation contrary to the tradition which had been held from the beginning, was very indignant at this.","verse":2}]}