{"author":"Jerome and Gennadius. Lives of Illustrious Men","book":"Gennadius. Lives of Illustrious Men.","chapter":91,"classification":{"bucket":"Patristic / broadly orthodox","canonicalStatus":"patristic","contentKind":"primary","cautionReason":"No major mainstream heresy warning is attached by the preview classifier.","doctrinalStatus":"orthodox","labels":["patristic"],"severity":0},"id":"npnf203:v.iv.xcii","lineage":["Jerome and Gennadius. Lives of Illustrious Men.","Gennadius. Lives of Illustrious Men.","Theodulus the presbyter."],"metadata":{"author":"Jerome and Gennadius. Lives of Illustrious Men","authorshipDateRange":null,"ccel":{"id":"npnf203","sourceUrl":"https://www.ccel.org/ccel/schaff/npnf203.xml","title":"NPNF2-03. Theodoret, Jerome, Gennadius, & Rufinus: Historical Writings"},"source":{"id":"npnf203","provider":"CCEL","sourceUrl":"https://www.ccel.org/ccel/schaff/npnf203.xml","title":"NPNF2-03. Theodoret, Jerome, Gennadius, & Rufinus: Historical Writings"}},"originalBook":null,"sourceVolumeId":"npnf203","title":"Theodulus the presbyter.","source":{"id":"npnf203","sourceUrl":"https://www.ccel.org/ccel/schaff/npnf203.xml","title":"NPNF2-03. Theodoret, Jerome, Gennadius, & Rufinus: Historical Writings"},"verses":[{"book":"Gennadius. Lives of Illustrious Men.","chapter":91,"text":"Theodulus, a presbyter in Coelesyria is said to have written many works, but the only one which has come to my hand, is the one which he composed On the harmony of divine Scripture, that is, the Scriptures of the Old and New Testaments, against the ancient heretics who on account of discrepancies in the injunctions of the ritual, say that the God of the Old Testament is different from the God of the New.","verse":1},{"book":"Gennadius. Lives of Illustrious Men.","chapter":91,"text":"In this work he shows it to have been by the dispensation of one and the same God, the author of both Scriptures, that one law should be given by Moses to those of old in a ritual of sacrifices and in judicial laws, and another to us through the presence of Christ in the holy mysteries and future promises, that they should not be considered different, but as dictated by one spirit and one author, since these things which if observed only according to the letter, would slay, if observed according to the spirit, would give life to the mind.","verse":2},{"book":"Gennadius. Lives of Illustrious Men.","chapter":91,"text":"This writer died three years since in the reign of Zeno.","verse":3}]}