{"author":"The Ecclesiastical History, Dialogues, and Letters of Theodoret","book":"Letters of the Blessed Theodoret, Bishop of Cyprus.","chapter":179,"classification":{"bucket":"Patristic / broadly orthodox","canonicalStatus":"patristic","contentKind":"primary","cautionReason":"No major mainstream heresy warning is attached by the preview classifier.","doctrinalStatus":"orthodox","labels":["patristic"],"severity":0},"id":"npnf203:iv.x.clxxix","lineage":["The Ecclesiastical History, Dialogues, and Letters of Theodoret.","Letters of the Blessed Theodoret, Bishop of Cyprus.","Letter to Alexander of Hierapolis."],"metadata":{"author":"The Ecclesiastical History, Dialogues, and Letters of Theodoret","authorshipDateRange":null,"ccel":{"id":"npnf203","sourceUrl":"https://www.ccel.org/ccel/schaff/npnf203.xml","title":"NPNF2-03. Theodoret, Jerome, Gennadius, & Rufinus: Historical Writings"},"source":{"id":"npnf203","provider":"CCEL","sourceUrl":"https://www.ccel.org/ccel/schaff/npnf203.xml","title":"NPNF2-03. Theodoret, Jerome, Gennadius, & Rufinus: Historical Writings"}},"originalBook":null,"sourceVolumeId":"npnf203","title":"Letter to Alexander of Hierapolis.","source":{"id":"npnf203","sourceUrl":"https://www.ccel.org/ccel/schaff/npnf203.xml","title":"NPNF2-03. Theodoret, Jerome, Gennadius, & Rufinus: Historical Writings"},"verses":[{"book":"Letters of the Blessed Theodoret, Bishop of Cyprus.","chapter":179,"text":"Letter to Alexander of Hierapolis.","verse":1},{"book":"Letters of the Blessed Theodoret, Bishop of Cyprus.","chapter":179,"text":"I think that more than all the very holy and venerable bishop, my lord John, must have been gratified at my refusing either to give my consent to the condemnation of the very holy and venerable bishop Nestorius or to violate the pledges made at Tarsus, Chalcedon and Ephesus.","verse":2},{"book":"Letters of the Blessed Theodoret, Bishop of Cyprus.","chapter":179,"text":"He remembers also what was frequently received from us at Antioch after our departure.","verse":3},{"book":"Letters of the Blessed Theodoret, Bishop of Cyprus.","chapter":179,"text":"Let no one therefore deceive your holiness into the belief that I should ever do this, for God is without doubt on my side and strengthening me.","verse":4}]}