{"author":null,"book":"The Ecclesiastical History of Socrates Scholasticus.","chapter":74,"classification":{"bucket":"Patristic / broadly orthodox","canonicalStatus":"patristic","contentKind":"primary","cautionReason":"No major mainstream heresy warning is attached by the preview classifier.","doctrinalStatus":"orthodox","labels":["patristic"],"severity":0},"id":"npnf202:ii.v.xxxiii","lineage":["The Ecclesiastical History of Socrates Scholasticus.","Book II","Of the Jews inhabiting Dio-Cæsarea in Palestine."],"metadata":{"author":null,"authorshipDateRange":null,"ccel":{"id":"npnf202","sourceUrl":"https://www.ccel.org/ccel/schaff/npnf202.xml","title":"NPNF2-02. Socrates and Sozomenus Ecclesiastical Histories"},"source":{"id":"npnf202","provider":"CCEL","sourceUrl":"https://www.ccel.org/ccel/schaff/npnf202.xml","title":"NPNF2-02. Socrates and Sozomenus Ecclesiastical Histories"}},"originalBook":"Book II","sourceVolumeId":"npnf202","title":"Of the Jews inhabiting Dio-Cæsarea in Palestine.","source":{"id":"npnf202","sourceUrl":"https://www.ccel.org/ccel/schaff/npnf202.xml","title":"NPNF2-02. Socrates and Sozomenus Ecclesiastical Histories"},"verses":[{"book":"The Ecclesiastical History of Socrates Scholasticus.","chapter":74,"text":"About the same time there arose another intestine commotion in the East: for the Jews who inhabited Dio-Cæsarea in Palestine took up arms against the Romans, and began to ravage the adjacent places.","verse":1},{"book":"The Ecclesiastical History of Socrates Scholasticus.","chapter":74,"text":"But Gallus who was also called Constantius, whom the emperor, after creating Cæsar, had sent into the East, despatched an army against them, and completely vanquished them: after which he ordered that their city Dio-Cæsarea should be razed to the foundations.","verse":2}]}